archipy/__init__.py
archipy/adapters/__init__.py
archipy/adapters/base/__init__.py
archipy/adapters/base/sqlalchemy/__init__.py
archipy/adapters/base/sqlalchemy/adapters.py
archipy/adapters/base/sqlalchemy/ports.py
archipy/adapters/base/sqlalchemy/session_manager_ports.py
archipy/adapters/base/sqlalchemy/session_manager_registry.py
archipy/adapters/base/sqlalchemy/session_managers.py
archipy/adapters/elasticsearch/__init__.py
archipy/adapters/elasticsearch/adapters.py
archipy/adapters/elasticsearch/ports.py
archipy/adapters/email/__init__.py
archipy/adapters/email/adapters.py
archipy/adapters/email/ports.py
archipy/adapters/internet_payment_gateways/__init__.py
archipy/adapters/internet_payment_gateways/ir/__init__.py
archipy/adapters/internet_payment_gateways/ir/parsian/__init__.py
archipy/adapters/internet_payment_gateways/ir/parsian/adapters.py
archipy/adapters/kafka/__init__.py
archipy/adapters/kafka/adapters.py
archipy/adapters/kafka/ports.py
archipy/adapters/keycloak/__init__.py
archipy/adapters/keycloak/adapters.py
archipy/adapters/keycloak/ports.py
archipy/adapters/minio/__init__.py
archipy/adapters/minio/adapters.py
archipy/adapters/minio/ports.py
archipy/adapters/postgres/__init__.py
archipy/adapters/postgres/sqlalchemy/__init__.py
archipy/adapters/postgres/sqlalchemy/adapters.py
archipy/adapters/postgres/sqlalchemy/session_manager_registry.py
archipy/adapters/postgres/sqlalchemy/session_managers.py
archipy/adapters/redis/__init__.py
archipy/adapters/redis/adapters.py
archipy/adapters/redis/mocks.py
archipy/adapters/redis/ports.py
archipy/adapters/scylladb/__init__.py
archipy/adapters/scylladb/adapters.py
archipy/adapters/scylladb/ports.py
archipy/adapters/sqlite/__init__.py
archipy/adapters/sqlite/sqlalchemy/__init__.py
archipy/adapters/sqlite/sqlalchemy/adapters.py
archipy/adapters/sqlite/sqlalchemy/session_manager_registry.py
archipy/adapters/sqlite/sqlalchemy/session_managers.py
archipy/adapters/starrocks/__init__.py
archipy-4.0.4.dist-info/METADATA
archipy-4.0.4.dist-info/WHEEL
archipy-4.0.4.dist-info/licenses/LICENSE
archipy-4.0.4.dist-info/RECORD
