Metadata-Version: 2.4
Name: archipy
Version: 4.0.4
Summary: Architecture + Python – Perfect for structured design.
Project-URL: Homepage, https://syntaxarc.github.io/ArchiPy/
Project-URL: Documentation, https://archipy.readthedocs.io/
Project-URL: Bug Tracker, https://github.com/SyntaxArc/ArchiPy/issues
Project-URL: Source Code, https://github.com/SyntaxArc/ArchiPy
Project-URL: Contributing, https://github.com/SyntaxArc/ArchiPy/blob/master/CONTRIBUTING.md
Project-URL: Code of Conduct, https://github.com/SyntaxArc/ArchiPy/blob/master/CODE_OF_CONDUCT.md
Author-email: Hossein Nejati <hosseinnejati14@gmail.com>, Mehdi Einali <einali@gmail.com>
License:                                  Apache License
License-File: LICENSE
Requires-Python: <4,>=3.14
Requires-Dist: jdatetime>=5.2.0
Requires-Dist: pydantic-settings>=2.12.0
Requires-Dist: pydantic>=2.12.5
Requires-Dist: requests>=2.32.5
Provides-Extra: aiosqlite
Requires-Dist: aiosqlite>=0.22.1; extra == 'aiosqlite'
Provides-Extra: behave
Requires-Dist: behave>=1.3.3; extra == 'behave'
Provides-Extra: cache
Requires-Dist: async-lru>=2.1.0; extra == 'cache'
Requires-Dist: cachetools>=6.2.6; extra == 'cache'
Provides-Extra: dependency-injection
Requires-Dist: dependency-injector>=4.48.3; extra == 'dependency-injection'
Provides-Extra: elastic-apm
Requires-Dist: elastic-apm>=6.25.0; extra == 'elastic-apm'
Provides-Extra: elasticsearch
Requires-Dist: elasticsearch>=9.2.1; extra == 'elasticsearch'
Provides-Extra: elasticsearch-async
Requires-Dist: elasticsearch[async]>=9.2.1; extra == 'elasticsearch-async'
Provides-Extra: fakeredis
Requires-Dist: fakeredis>=2.33.0; extra == 'fakeredis'
Provides-Extra: fastapi
Requires-Dist: fastapi[all]>=0.128.0; extra == 'fastapi'
Provides-Extra: grpc
Requires-Dist: grpcio-health-checking>=1.76.0; extra == 'grpc'
Requires-Dist: grpcio>=1.76.0; extra == 'grpc'
Requires-Dist: protobuf>=6.33.5; extra == 'grpc'
Provides-Extra: jwt
Requires-Dist: pyjwt>=2.11.0; extra == 'jwt'
Provides-Extra: kafka
Requires-Dist: confluent-kafka>=2.13.0; extra == 'kafka'
Provides-Extra: kavenegar
Requires-Dist: kavenegar>=1.1.2; extra == 'kavenegar'
Provides-Extra: keycloak
Requires-Dist: async-lru>=2.1.0; extra == 'keycloak'
Requires-Dist: cachetools>=6.2.6; extra == 'keycloak'
Requires-Dist: python-keycloak>=7.0.3; extra == 'keycloak'
Provides-Extra: minio
Requires-Dist: async-lru>=2.1.0; extra == 'minio'
Requires-Dist: cachetools>=6.2.6; extra == 'minio'
Requires-Dist: minio>=7.2.20; extra == 'minio'
Provides-Extra: parsian-ipg
Requires-Dist: requests[socks]>=2.32.5; extra == 'parsian-ipg'
Requires-Dist: zeep>=4.3.2; extra == 'parsian-ipg'
Provides-Extra: postgres
Requires-Dist: psycopg[binary,pool]>=3.3.2; extra == 'postgres'
Provides-Extra: prometheus
Requires-Dist: prometheus-client>=0.24.1; extra == 'prometheus'
Provides-Extra: redis
Requires-Dist: redis[hiredis]>=7.1.0; extra == 'redis'
Provides-Extra: scheduler
Requires-Dist: apscheduler>=3.11.2; extra == 'scheduler'
Provides-Extra: scylladb
Requires-Dist: async-lru>=2.1.0; extra == 'scylladb'
Requires-Dist: cachetools>=6.2.6; extra == 'scylladb'
Requires-Dist: lz4>=4.4.5; extra == 'scylladb'
Requires-Dist: scylla-driver>=3.29.7; extra == 'scylladb'
Provides-Extra: sentry
Requires-Dist: sentry-sdk>=2.51.0; extra == 'sentry'
Provides-Extra: sqlalchemy
Requires-Dist: sqlalchemy>=2.0.46; extra == 'sqlalchemy'
Provides-Extra: sqlalchemy-async
Requires-Dist: sqlalchemy[asyncio]>=2.0.46; extra == 'sqlalchemy-async'
Provides-Extra: starrocks
Requires-Dist: pymysql>=1.1.2; extra == 'starrocks'
Requires-Dist: starrocks>=1.3.3; extra == 'starrocks'
Provides-Extra: starrocks-async
Requires-Dist: aiomysql>=0.3.2; extra == 'starrocks-async'
Requires-Dist: starrocks>=1.3.3; extra == 'starrocks-async'
Provides-Extra: temporalio
Requires-Dist: temporalio>=1.21.1; extra == 'temporalio'
Provides-Extra: testcontainers
Requires-Dist: testcontainers>=4.14.0; extra == 'testcontainers'
